setup.py
sdpc/Sdpc.py
sdpc/Sdpc_struct.py
sdpc/__init__.py
sdpc/DLL/DecodeHevc.lib
sdpc/DLL/DecodeSdpcDll.lib
sdpc/DLL/avcodec.lib
sdpc/DLL/avdevice.lib
sdpc/DLL/avfilter.lib
sdpc/DLL/avformat.lib
sdpc/DLL/avutil.lib
sdpc/DLL/postproc.lib
sdpc/DLL/swresample.lib
sdpc/DLL/swscale.lib
sdpc/DLL/turbojpeg-static.lib
sdpc/DLL/dll/DecodeHevc.dll
sdpc/DLL/dll/DecodeSdpcDll.dll
sdpc/DLL/dll/avcodec-58.dll
sdpc/DLL/dll/avdevice-58.dll
sdpc/DLL/dll/avfilter-7.dll
sdpc/DLL/dll/avformat-58.dll
sdpc/DLL/dll/avutil-56.dll
sdpc/DLL/dll/postproc-55.dll
sdpc/DLL/dll/swresample-3.dll
sdpc/DLL/dll/swscale-5.dll
sdpc_win.egg-info/PKG-INFO
sdpc_win.egg-info/SOURCES.txt
sdpc_win.egg-info/dependency_links.txt
sdpc_win.egg-info/requires.txt
sdpc_win.egg-info/top_level.txt