Metadata-Version: 2.1
Name: sdpc-win
Version: 2.0
Summary: a library for sdpcPY (windows version)
Home-page: https://github.com/THU-JWonderLand/sdpcPY-win
Author: Qiming He, Renao Yan, Yiqing Liu, Jiawen Li
Author-email: lijiawen21@mails.tsinghua.edu.cn
License: MIT License
Platform: windows
